greentext_scraper/__init__.py
greentext_scraper/scraper.py
greentext_scraper-1.0.0.dist-info/LICENSE
greentext_scraper-1.0.0.dist-info/METADATA
greentext_scraper-1.0.0.dist-info/WHEEL
greentext_scraper-1.0.0.dist-info/top_level.txt
greentext_scraper-1.0.0.dist-info/RECORD
