Metadata-Version: 2.1
Name: greentext-scraper
Version: 1.0.0
Summary: Python library to scrape all greentexts from active 4chan threads
Author: Christian Fiore
License: GNU GENERAL PUBLIC LICENSE
Project-URL: Homepage, https://github.com/agente3z/greentext-scraper
License-File: LICENSE
Requires-Dist: basc-py4chan
